setup.py
dsnd_probability_jlfsjr/Binomialdistribution.py
dsnd_probability_jlfsjr/Gaussiandistribution.py
dsnd_probability_jlfsjr/Generaldistribution.py
dsnd_probability_jlfsjr/__init__.py
dsnd_probability_jlfsjr.egg-info/PKG-INFO
dsnd_probability_jlfsjr.egg-info/SOURCES.txt
dsnd_probability_jlfsjr.egg-info/dependency_links.txt
dsnd_probability_jlfsjr.egg-info/not-zip-safe
dsnd_probability_jlfsjr.egg-info/top_level.txt