Metadata-Version: 1.0
Name: dsnd-probability-jlfsjr
Version: 1.0
Summary: Gaussian and Binomial distributions
Home-page: UNKNOWN
Author: Jorge Luiz Figueira
Author-email: jorgeluizfigueira@gmail.com
License: UNKNOWN
Platform: UNKNOWN
